drf_social_oauth2/__init__.py
drf_social_oauth2/authentication.py
drf_social_oauth2/backends.py
drf_social_oauth2/forms.py
drf_social_oauth2/models.py
drf_social_oauth2/oauth2_backends.py
drf_social_oauth2/oauth2_endpoints.py
drf_social_oauth2/oauth2_grants.py
drf_social_oauth2/pipeline.py
drf_social_oauth2/serializers.py
drf_social_oauth2/settings.py
drf_social_oauth2/test_settings.py
drf_social_oauth2/urls.py
drf_social_oauth2/views.py
drf_social_oauth2/migrations/0001_add_multi_factor_code_model.py
drf_social_oauth2/migrations/0001_initial.py
drf_social_oauth2/migrations/ola.py
tests/__init__.py
tests/drf_social_oauth2/__init__.py
tests/drf_social_oauth2/drf_fixtures.py
tests/drf_social_oauth2/test_authentication.py
tests/drf_social_oauth2/test_oauth2_endpoints.py
tests/drf_social_oauth2/test_views.py
drf_social_oauth2-2.1.3.dist-info/LICENSE.txt
drf_social_oauth2-2.1.3.dist-info/METADATA
drf_social_oauth2-2.1.3.dist-info/WHEEL
drf_social_oauth2-2.1.3.dist-info/top_level.txt
drf_social_oauth2-2.1.3.dist-info/RECORD
