Metadata-Version: 2.1
Name: drf-social-oauth2
Version: 2.1.3
Summary:  drf-social-oauth2 is a frameworks meant to be used with Django and Django Rest Framework. drf-social-oauth2 offers support to oauth2 authentication and authorization. It's one of the easiest frameworks to integrate Oauth2 to your Django Rest Framework application. By using drf-social-oauth2 you can authenticate with major vendors such as Google, Facebook, Instagram, Github, Twitter and a ton more! 
Home-page: https://github.com/wagnerdelima/drf-social-oauth2
Author: Wagner de Lima
Author-email: waglds@gmail.com
License: MIT
Platform: UNKNOWN
Classifier: Development Status :: 5 - Production/Stable
Classifier: Environment :: Web Environment
Classifier: Framework :: Django
Classifier: License :: OSI Approved :: MIT License
Classifier: Programming Language :: Python :: 3
Classifier: Topic :: Internet :: WWW/HTTP
Classifier: Topic :: Software Development :: Libraries :: Python Modules
Classifier: Intended Audience :: Developers
Classifier: Intended Audience :: Information Technology
Classifier: Natural Language :: English
License-File: LICENSE.txt
